django_easy_pdf-0.2.0.dev1.dist-info/DESCRIPTION.rst
django_easy_pdf-0.2.0.dev1.dist-info/LICENSE.txt
django_easy_pdf-0.2.0.dev1.dist-info/METADATA
django_easy_pdf-0.2.0.dev1.dist-info/RECORD
django_easy_pdf-0.2.0.dev1.dist-info/WHEEL
django_easy_pdf-0.2.0.dev1.dist-info/metadata.json
django_easy_pdf-0.2.0.dev1.dist-info/top_level.txt
easy_pdf/__init__.py
easy_pdf/apps.py
easy_pdf/models.py
easy_pdf/rendering.py
easy_pdf/tests.py
easy_pdf/views.py
easy_pdf/templates/easy_pdf/base.html
